LICENSE
README.md
setup.py
wiki_data_dump/__init__.py
wiki_data_dump/api_response.py
wiki_data_dump/cache.py
wiki_data_dump/core.py
wiki_data_dump/download.py
wiki_data_dump/mirrors.py
wiki_data_dump.egg-info/PKG-INFO
wiki_data_dump.egg-info/SOURCES.txt
wiki_data_dump.egg-info/dependency_links.txt
wiki_data_dump.egg-info/requires.txt
wiki_data_dump.egg-info/top_level.txt