Metadata-Version: 2.1
Name: wiki-data-dump
Version: 0.0.4
Summary: A package for traversing and downloading files from Wiki Data Dump mirrors.
Home-page: https://github.com/jon-edward/wiki_dump
Author: jon-edward
Author-email: arithmatlic@gmail.com
License: UNKNOWN
Keywords: wikimedia,wiki data dumps,wikipedia
Platform: UNKNOWN
Classifier: Programming Language :: Python :: 3
Classifier: License :: OSI Approved :: MIT License
Classifier: Operating System :: OS Independent
Requires-Python: >=3.8
License-File: LICENSE
